{
  "seasonId": "season-01-broken-signal",
  "missions": [
    {
      "id": "story-s01-m01",
      "storyBeatId": "beat-s01-001",
      "missionIndex": 1,
      "chapterId": "ch-01",
      "title": "Registry Wake",
      "titleJa": "レジストリ覚醒",
      "template": {
        "type": "VOCABULARY",
        "gameMode": "STANDARD",
        "wordCount": 3,
        "narrativeTier": "MAIN",
        "seasonId": "season-01-broken-signal",
        "chapterId": "ch-01",
        "missionIndex": 1,
        "storyBeatId": "beat-s01-001",
        "linkedSectorId": "sector-01",
        "description": "Registry Wake — Season 1 main operation.",
        "briefing": "Registry dispatch — registry wake protocol active.",
        "minimumLevel": 1
      }
    },
    {
      "id": "story-s01-m02",
      "storyBeatId": "beat-s01-002",
      "missionIndex": 2,
      "chapterId": "ch-01",
      "title": "First Glyph",
      "titleJa": "第一の文字",
      "template": {
        "type": "VOCABULARY",
        "gameMode": "TERMINAL_BREACH",
        "prerequisiteBeatId": "beat-s01-001",
        "wordCount": 3,
        "narrativeTier": "MAIN",
        "seasonId": "season-01-broken-signal",
        "chapterId": "ch-01",
        "missionIndex": 2,
        "storyBeatId": "beat-s01-002",
        "archiveUnlockId": "corridor-zero",
        "linkedSectorId": "sector-01",
        "description": "First Glyph — Season 1 main operation.",
        "briefing": "Registry dispatch — first glyph protocol active.",
        "minimumLevel": 1
      }
    },
    {
      "id": "story-s01-m03",
      "storyBeatId": "beat-s01-003",
      "missionIndex": 3,
      "chapterId": "ch-01",
      "title": "Silent Prayer",
      "titleJa": "静かな祈り",
      "template": {
        "type": "LISTENING",
        "gameMode": "LOST_TRANSMISSION",
        "prerequisiteBeatId": "beat-s01-002",
        "wordCount": 3,
        "narrativeTier": "MAIN",
        "seasonId": "season-01-broken-signal",
        "chapterId": "ch-01",
        "missionIndex": 3,
        "storyBeatId": "beat-s01-003",
        "linkedSectorId": "sector-01",
        "description": "Silent Prayer — Season 1 main operation.",
        "briefing": "Registry dispatch — silent prayer protocol active.",
        "minimumLevel": 1
      }
    },
    {
      "id": "story-s01-m04",
      "storyBeatId": "beat-s01-004",
      "missionIndex": 4,
      "chapterId": "ch-01",
      "title": "Iris Briefing",
      "titleJa": "アイリスブリーフィング",
      "template": {
        "type": "CONVERSATION",
        "gameMode": "GHOST_INTERROGATION",
        "prerequisiteBeatId": "beat-s01-003",
        "narrativeTier": "MAIN",
        "seasonId": "season-01-broken-signal",
        "chapterId": "ch-01",
        "missionIndex": 4,
        "storyBeatId": "beat-s01-004",
        "archiveUnlockId": "whisper-index",
        "scenarioId": "iris-briefing",
        "linkedSectorId": "sector-01",
        "description": "Iris Briefing — Season 1 main operation.",
        "briefing": "Registry dispatch — iris briefing protocol active.",
        "minimumLevel": 1
      }
    },
    {
      "id": "story-s01-m05",
      "storyBeatId": "beat-s01-005",
      "missionIndex": 5,
      "chapterId": "ch-01",
      "title": "Temple Signal",
      "titleJa": "寺院信号",
      "template": {
        "type": "LISTENING",
        "gameMode": "ECHO_LISTENING",
        "prerequisiteBeatId": "beat-s01-004",
        "wordCount": 3,
        "narrativeTier": "MAIN",
        "seasonId": "season-01-broken-signal",
        "chapterId": "ch-01",
        "missionIndex": 5,
        "storyBeatId": "beat-s01-005",
        "linkedSectorId": "sector-01",
        "description": "Temple Signal — Season 1 main operation.",
        "briefing": "Registry dispatch — temple signal protocol active.",
        "minimumLevel": 1
      }
    },
    {
      "id": "story-s01-m06",
      "storyBeatId": "beat-s01-006",
      "missionIndex": 6,
      "chapterId": "ch-01",
      "title": "Forgotten Names",
      "titleJa": "忘れられた名",
      "template": {
        "type": "VOCABULARY",
        "gameMode": "MEMORY_CASCADE",
        "prerequisiteBeatId": "beat-s01-005",
        "wordCount": 4,
        "narrativeTier": "MAIN",
        "seasonId": "season-01-broken-signal",
        "chapterId": "ch-01",
        "missionIndex": 6,
        "storyBeatId": "beat-s01-006",
        "linkedSectorId": "sector-01",
        "description": "Forgotten Names — Season 1 main operation.",
        "briefing": "Registry dispatch — forgotten names protocol active.",
        "minimumLevel": 1
      }
    },
    {
      "id": "story-s01-m07",
      "storyBeatId": "beat-s01-007",
      "missionIndex": 7,
      "chapterId": "ch-01",
      "title": "Archive Restoration",
      "titleJa": "記録復元",
      "template": {
        "type": "VOCABULARY",
        "gameMode": "KANJI_SURGERY",
        "prerequisiteBeatId": "beat-s01-006",
        "wordCount": 4,
        "narrativeTier": "MAIN",
        "seasonId": "season-01-broken-signal",
        "chapterId": "ch-01",
        "missionIndex": 7,
        "storyBeatId": "beat-s01-007",
        "linkedSectorId": "sector-01",
        "description": "Archive Restoration — Season 1 main operation.",
        "briefing": "Registry dispatch — archive restoration protocol active.",
        "minimumLevel": 2
      }
    },
    {
      "id": "story-s01-m08",
      "storyBeatId": "beat-s01-008",
      "missionIndex": 8,
      "chapterId": "ch-01",
      "title": "Hollow Gate",
      "titleJa": "虚ろの門",
      "template": {
        "type": "VOCABULARY",
        "gameMode": "STANDARD",
        "prerequisiteBeatId": "beat-s01-007",
        "wordCount": 5,
        "narrativeTier": "MAIN",
        "seasonId": "season-01-broken-signal",
        "chapterId": "ch-01",
        "missionIndex": 8,
        "storyBeatId": "beat-s01-008",
        "linkedSectorId": "sector-01",
        "description": "Hollow Gate — Season 1 main operation.",
        "briefing": "Registry dispatch — hollow gate protocol active.",
        "minimumLevel": 2
      }
    },
    {
      "id": "story-s01-m09",
      "storyBeatId": "beat-s01-009",
      "missionIndex": 9,
      "chapterId": "ch-02",
      "title": "Distorted Broadcast",
      "titleJa": "歪んだ放送",
      "template": {
        "type": "LISTENING",
        "gameMode": "LOST_TRANSMISSION",
        "prerequisiteBeatId": "beat-s01-008",
        "wordCount": 3,
        "narrativeTier": "MAIN",
        "seasonId": "season-01-broken-signal",
        "chapterId": "ch-02",
        "missionIndex": 9,
        "storyBeatId": "beat-s01-009",
        "linkedSectorId": "sector-02",
        "description": "Distorted Broadcast — Season 1 main operation.",
        "briefing": "Registry dispatch — distorted broadcast protocol active.",
        "minimumLevel": 2
      }
    },
    {
      "id": "story-s01-m10",
      "storyBeatId": "beat-s01-010",
      "missionIndex": 10,
      "chapterId": "ch-02",
      "title": "Neon Infiltration",
      "titleJa": "ネオン潜入",
      "template": {
        "type": "VOCABULARY",
        "gameMode": "TERMINAL_BREACH",
        "prerequisiteBeatId": "beat-s01-009",
        "wordCount": 4,
        "narrativeTier": "MAIN",
        "seasonId": "season-01-broken-signal",
        "chapterId": "ch-02",
        "missionIndex": 10,
        "storyBeatId": "beat-s01-010",
        "linkedSectorId": "sector-02",
        "description": "Neon Infiltration — Season 1 main operation.",
        "briefing": "Registry dispatch — neon infiltration protocol active.",
        "minimumLevel": 3
      }
    },
    {
      "id": "story-s01-m11",
      "storyBeatId": "beat-s01-011",
      "missionIndex": 11,
      "chapterId": "ch-02",
      "title": "Operator Seven",
      "titleJa": "オペレーター七",
      "template": {
        "type": "CONVERSATION",
        "gameMode": "DEEP_COVER",
        "prerequisiteBeatId": "beat-s01-010",
        "narrativeTier": "MAIN",
        "seasonId": "season-01-broken-signal",
        "chapterId": "ch-02",
        "missionIndex": 11,
        "storyBeatId": "beat-s01-011",
        "archiveUnlockId": "neon-grid-failure",
        "scenarioId": "operator-seven",
        "linkedSectorId": "sector-02",
        "description": "Operator Seven — Season 1 main operation.",
        "briefing": "Registry dispatch — operator seven protocol active.",
        "minimumLevel": 3
      }
    },
    {
      "id": "story-s01-m12",
      "storyBeatId": "beat-s01-012",
      "missionIndex": 12,
      "chapterId": "ch-02",
      "title": "Emergency Transmission",
      "titleJa": "緊急送信",
      "template": {
        "type": "SPEECH",
        "gameMode": "SHADOW_ECHO",
        "prerequisiteBeatId": "beat-s01-011",
        "narrativeTier": "MAIN",
        "seasonId": "season-01-broken-signal",
        "chapterId": "ch-02",
        "missionIndex": 12,
        "storyBeatId": "beat-s01-012",
        "scenarioId": "field-relay",
        "linkedSectorId": "sector-02",
        "description": "Emergency Transmission — Season 1 main operation.",
        "briefing": "Registry dispatch — emergency transmission protocol active.",
        "minimumLevel": 3
      }
    },
    {
      "id": "story-s01-m13",
      "storyBeatId": "beat-s01-013",
      "missionIndex": 13,
      "chapterId": "ch-02",
      "title": "Corridor Breach",
      "titleJa": "回廊突破",
      "template": {
        "type": "DUNGEON",
        "gameMode": "STANDARD",
        "prerequisiteBeatId": "beat-s01-012",
        "narrativeTier": "MAIN",
        "seasonId": "season-01-broken-signal",
        "chapterId": "ch-02",
        "missionIndex": 13,
        "storyBeatId": "beat-s01-013",
        "linkedSectorId": "sector-02",
        "linkedDungeonKey": "dungeon:neon-corridor",
        "description": "Corridor Breach — Season 1 main operation.",
        "briefing": "Registry dispatch — corridor breach protocol active.",
        "minimumLevel": 4
      }
    },
    {
      "id": "story-s01-m14",
      "storyBeatId": "beat-s01-014",
      "missionIndex": 14,
      "chapterId": "ch-02",
      "title": "Warden Rematch",
      "titleJa": "監視者再戦",
      "template": {
        "type": "DUNGEON",
        "gameMode": "STANDARD",
        "prerequisiteBeatId": "beat-s01-013",
        "narrativeTier": "MAIN",
        "seasonId": "season-01-broken-signal",
        "chapterId": "ch-02",
        "missionIndex": 14,
        "storyBeatId": "beat-s01-014",
        "archiveUnlockId": "warden-phase-two",
        "linkedSectorId": "sector-02",
        "linkedDungeonKey": "dungeon:neon-corridor",
        "description": "Warden Rematch — Season 1 main operation.",
        "briefing": "Registry dispatch — warden rematch protocol active.",
        "minimumLevel": 4
      }
    },
    {
      "id": "story-s01-m15",
      "storyBeatId": "beat-s01-015",
      "missionIndex": 15,
      "chapterId": "ch-02",
      "title": "Static Confession",
      "titleJa": "静止告白",
      "template": {
        "type": "CONVERSATION",
        "gameMode": "GHOST_INTERROGATION",
        "prerequisiteBeatId": "beat-s01-014",
        "narrativeTier": "MAIN",
        "seasonId": "season-01-broken-signal",
        "chapterId": "ch-02",
        "missionIndex": 15,
        "storyBeatId": "beat-s01-015",
        "archiveUnlockId": "iris-routing-table",
        "scenarioId": "static-confession",
        "linkedSectorId": "sector-02",
        "description": "Static Confession — Season 1 main operation.",
        "briefing": "Registry dispatch — static confession protocol active.",
        "minimumLevel": 4
      }
    },
    {
      "id": "story-s01-m16",
      "storyBeatId": "beat-s01-016",
      "missionIndex": 16,
      "chapterId": "ch-02",
      "title": "Signal Crown",
      "titleJa": "信号の冠",
      "template": {
        "type": "VOCABULARY",
        "gameMode": "SURVIVAL_VOCAB",
        "prerequisiteBeatId": "beat-s01-015",
        "wordCount": 5,
        "narrativeTier": "MAIN",
        "seasonId": "season-01-broken-signal",
        "chapterId": "ch-02",
        "missionIndex": 16,
        "storyBeatId": "beat-s01-016",
        "linkedSectorId": "sector-02",
        "description": "Signal Crown — Season 1 main operation.",
        "briefing": "Registry dispatch — signal crown protocol active.",
        "minimumLevel": 5
      }
    },
    {
      "id": "story-s01-m17",
      "storyBeatId": "beat-s01-017",
      "missionIndex": 17,
      "chapterId": "ch-03",
      "title": "Lexicon Debt",
      "titleJa": "語彙の負債",
      "template": {
        "type": "VOCABULARY",
        "gameMode": "MEMORY_CASCADE",
        "prerequisiteBeatId": "beat-s01-016",
        "wordCount": 5,
        "narrativeTier": "MAIN",
        "seasonId": "season-01-broken-signal",
        "chapterId": "ch-03",
        "missionIndex": 17,
        "storyBeatId": "beat-s01-017",
        "linkedSectorId": "sector-03",
        "description": "Lexicon Debt — Season 1 main operation.",
        "briefing": "Registry dispatch — lexicon debt protocol active.",
        "minimumLevel": 5
      }
    },
    {
      "id": "story-s01-m18",
      "storyBeatId": "beat-s01-018",
      "missionIndex": 18,
      "chapterId": "ch-03",
      "title": "Archivist Contact",
      "titleJa": "記録官接触",
      "template": {
        "type": "CONVERSATION",
        "gameMode": "GHOST_INTERROGATION",
        "prerequisiteBeatId": "beat-s01-017",
        "narrativeTier": "MAIN",
        "seasonId": "season-01-broken-signal",
        "chapterId": "ch-03",
        "missionIndex": 18,
        "storyBeatId": "beat-s01-018",
        "scenarioId": "shadow-briefing",
        "linkedSectorId": "sector-03",
        "description": "Archivist Contact — Season 1 main operation.",
        "briefing": "Registry dispatch — archivist contact protocol active.",
        "minimumLevel": 5
      }
    },
    {
      "id": "story-s01-m19",
      "storyBeatId": "beat-s01-019",
      "missionIndex": 19,
      "chapterId": "ch-03",
      "title": "Memory Vault",
      "titleJa": "記憶保管庫",
      "template": {
        "type": "LISTENING",
        "gameMode": "LOST_TRANSMISSION",
        "prerequisiteBeatId": "beat-s01-018",
        "wordCount": 4,
        "narrativeTier": "MAIN",
        "seasonId": "season-01-broken-signal",
        "chapterId": "ch-03",
        "missionIndex": 19,
        "storyBeatId": "beat-s01-019",
        "linkedSectorId": "sector-03",
        "description": "Memory Vault — Season 1 main operation.",
        "briefing": "Registry dispatch — memory vault protocol active.",
        "minimumLevel": 6
      }
    },
    {
      "id": "story-s01-m20",
      "storyBeatId": "beat-s01-020",
      "missionIndex": 20,
      "chapterId": "ch-03",
      "title": "Shadow Breach",
      "titleJa": "影の突破",
      "template": {
        "type": "DUNGEON",
        "gameMode": "ARCHIVIST_BOSS",
        "prerequisiteBeatId": "beat-s01-019",
        "narrativeTier": "MAIN",
        "seasonId": "season-01-broken-signal",
        "chapterId": "ch-03",
        "missionIndex": 20,
        "storyBeatId": "beat-s01-020",
        "archiveUnlockId": "semantic-collapse",
        "linkedSectorId": "sector-03",
        "linkedDungeonKey": "dungeon:shadow-archive",
        "description": "Shadow Breach — Season 1 main operation.",
        "briefing": "Registry dispatch — shadow breach protocol active.",
        "minimumLevel": 6
      }
    },
    {
      "id": "story-s01-m21",
      "storyBeatId": "beat-s01-021",
      "missionIndex": 21,
      "chapterId": "ch-03",
      "title": "Forbidden Index",
      "titleJa": "禁断索引",
      "template": {
        "type": "VOCABULARY",
        "gameMode": "ENTITY_HUNT",
        "prerequisiteBeatId": "beat-s01-020",
        "wordCount": 5,
        "narrativeTier": "MAIN",
        "seasonId": "season-01-broken-signal",
        "chapterId": "ch-03",
        "missionIndex": 21,
        "storyBeatId": "beat-s01-021",
        "linkedSectorId": "sector-03",
        "description": "Forbidden Index — Season 1 main operation.",
        "briefing": "Registry dispatch — forbidden index protocol active.",
        "minimumLevel": 6
      }
    },
    {
      "id": "story-s01-m22",
      "storyBeatId": "beat-s01-022",
      "missionIndex": 22,
      "chapterId": "ch-03",
      "title": "Iris Truth",
      "titleJa": "アイリスの真実",
      "template": {
        "type": "CONVERSATION",
        "gameMode": "DEEP_COVER",
        "prerequisiteBeatId": "beat-s01-021",
        "narrativeTier": "MAIN",
        "seasonId": "season-01-broken-signal",
        "chapterId": "ch-03",
        "missionIndex": 22,
        "storyBeatId": "beat-s01-022",
        "scenarioId": "iris-truth",
        "linkedSectorId": "sector-03",
        "description": "Iris Truth — Season 1 main operation.",
        "briefing": "Registry dispatch — iris truth protocol active.",
        "minimumLevel": 7
      }
    },
    {
      "id": "story-s01-m23",
      "storyBeatId": "beat-s01-023",
      "missionIndex": 23,
      "chapterId": "ch-04",
      "title": "Abyss Probe",
      "titleJa": "深淵探査",
      "template": {
        "type": "DUNGEON",
        "gameMode": "STANDARD",
        "prerequisiteBeatId": "beat-s01-022",
        "narrativeTier": "MAIN",
        "seasonId": "season-01-broken-signal",
        "chapterId": "ch-04",
        "missionIndex": 23,
        "storyBeatId": "beat-s01-023",
        "archiveUnlockId": "void-priest-fragment",
        "linkedSectorId": "sector-04",
        "linkedDungeonKey": "dungeon:abyss-core",
        "description": "Abyss Probe — Season 1 main operation.",
        "briefing": "Registry dispatch — abyss probe protocol active.",
        "minimumLevel": 7
      }
    },
    {
      "id": "story-s01-m24",
      "storyBeatId": "beat-s01-024",
      "missionIndex": 24,
      "chapterId": "ch-04",
      "title": "Broken Signal Finale",
      "titleJa": "壊れた信号",
      "template": {
        "type": "CONVERSATION",
        "gameMode": "SEMANTIC_NETWORK",
        "prerequisiteBeatId": "beat-s01-023",
        "narrativeTier": "MAIN",
        "seasonId": "season-01-broken-signal",
        "chapterId": "ch-04",
        "missionIndex": 24,
        "storyBeatId": "beat-s01-024",
        "archiveUnlockId": "extraction-oath",
        "scenarioId": "broken-signal-finale",
        "linkedSectorId": "sector-04",
        "description": "Broken Signal Finale — Season 1 main operation.",
        "briefing": "Registry dispatch — broken signal finale protocol active.",
        "minimumLevel": 7
      }
    }
  ]
}